setup.py
pDtlabCsCovea2/_init_.py
pDtlabCsCovea2.egg-info/PKG-INFO
pDtlabCsCovea2.egg-info/SOURCES.txt
pDtlabCsCovea2.egg-info/dependency_links.txt
pDtlabCsCovea2.egg-info/not-zip-safe
pDtlabCsCovea2.egg-info/top_level.txt