Metadata-Version: 1.0
Name: pDtlabCsCovea2
Version: 0.1
Summary: Package Datalab
Home-page: http://github.com/.../...
Author: coveadtlabteam123
Author-email: dtlab-team@getnada.com
License: MIT
Platform: UNKNOWN
